{"expireTime":9007200897497633000,"key":"gatsby-plugin-mdx-entire-payload-c7d4cb9e2a1a5b1466f19970697500d8-","val":{"mdast":{"type":"root","children":[{"type":"import","value":"import DefaultLayout from \"/Users/bobby/Sites/github.com/nl-design-system/documentatie/node_modules/gatsby-theme-docz/src/base/Layout.js\"","position":{"start":{"line":3,"column":1,"offset":2},"end":{"line":3,"column":138,"offset":139},"indent":[]}},{"type":"export","default":true,"value":"export default DefaultLayout","position":{"start":{"line":5,"column":1,"offset":141},"end":{"line":5,"column":29,"offset":169},"indent":[]}},{"type":"jsx","value":"<!-- @license CC0-1.0 -->","position":{"start":{"line":7,"column":1,"offset":171},"end":{"line":7,"column":26,"offset":196},"indent":[]}},{"type":"heading","depth":1,"children":[{"type":"text","value":"Headings","position":{"start":{"line":9,"column":3,"offset":200},"end":{"line":9,"column":11,"offset":208},"indent":[]}}],"position":{"start":{"line":9,"column":1,"offset":198},"end":{"line":9,"column":11,"offset":208},"indent":[]}},{"type":"paragraph","children":[{"type":"text","value":"This applies to multiple heading components:","position":{"start":{"line":11,"column":1,"offset":210},"end":{"line":11,"column":45,"offset":254},"indent":[]}}],"position":{"start":{"line":11,"column":1,"offset":210},"end":{"line":11,"column":45,"offset":254},"indent":[]}},{"type":"list","ordered":false,"start":null,"spread":false,"children":[{"type":"listItem","spread":false,"checked":null,"children":[{"type":"paragraph","children":[{"type":"inlineCode","value":"<h1>","position":{"start":{"line":13,"column":5,"offset":260},"end":{"line":13,"column":11,"offset":266},"indent":[]}},{"type":"text","value":" and ","position":{"start":{"line":13,"column":11,"offset":266},"end":{"line":13,"column":16,"offset":271},"indent":[]}},{"type":"inlineCode","value":"role=\"heading\" aria-level=\"1\"","position":{"start":{"line":13,"column":16,"offset":271},"end":{"line":13,"column":47,"offset":302},"indent":[]}}],"position":{"start":{"line":13,"column":5,"offset":260},"end":{"line":13,"column":47,"offset":302},"indent":[]}}],"position":{"start":{"line":13,"column":1,"offset":256},"end":{"line":13,"column":47,"offset":302},"indent":[]}},{"type":"listItem","spread":false,"checked":null,"children":[{"type":"paragraph","children":[{"type":"inlineCode","value":"<h2>","position":{"start":{"line":14,"column":5,"offset":307},"end":{"line":14,"column":11,"offset":313},"indent":[]}},{"type":"text","value":" and ","position":{"start":{"line":14,"column":11,"offset":313},"end":{"line":14,"column":16,"offset":318},"indent":[]}},{"type":"inlineCode","value":"role=\"heading\" aria-level=\"2\"","position":{"start":{"line":14,"column":16,"offset":318},"end":{"line":14,"column":47,"offset":349},"indent":[]}}],"position":{"start":{"line":14,"column":5,"offset":307},"end":{"line":14,"column":47,"offset":349},"indent":[]}}],"position":{"start":{"line":14,"column":1,"offset":303},"end":{"line":14,"column":47,"offset":349},"indent":[]}},{"type":"listItem","spread":false,"checked":null,"children":[{"type":"paragraph","children":[{"type":"inlineCode","value":"<h3>","position":{"start":{"line":15,"column":5,"offset":354},"end":{"line":15,"column":11,"offset":360},"indent":[]}},{"type":"text","value":" and ","position":{"start":{"line":15,"column":11,"offset":360},"end":{"line":15,"column":16,"offset":365},"indent":[]}},{"type":"inlineCode","value":"role=\"heading\" aria-level=\"3\"","position":{"start":{"line":15,"column":16,"offset":365},"end":{"line":15,"column":47,"offset":396},"indent":[]}}],"position":{"start":{"line":15,"column":5,"offset":354},"end":{"line":15,"column":47,"offset":396},"indent":[]}}],"position":{"start":{"line":15,"column":1,"offset":350},"end":{"line":15,"column":47,"offset":396},"indent":[]}},{"type":"listItem","spread":false,"checked":null,"children":[{"type":"paragraph","children":[{"type":"inlineCode","value":"<h4>","position":{"start":{"line":16,"column":5,"offset":401},"end":{"line":16,"column":11,"offset":407},"indent":[]}},{"type":"text","value":" and ","position":{"start":{"line":16,"column":11,"offset":407},"end":{"line":16,"column":16,"offset":412},"indent":[]}},{"type":"inlineCode","value":"role=\"heading\" aria-level=\"4\"","position":{"start":{"line":16,"column":16,"offset":412},"end":{"line":16,"column":47,"offset":443},"indent":[]}}],"position":{"start":{"line":16,"column":5,"offset":401},"end":{"line":16,"column":47,"offset":443},"indent":[]}}],"position":{"start":{"line":16,"column":1,"offset":397},"end":{"line":16,"column":47,"offset":443},"indent":[]}},{"type":"listItem","spread":false,"checked":null,"children":[{"type":"paragraph","children":[{"type":"inlineCode","value":"<h5>","position":{"start":{"line":17,"column":5,"offset":448},"end":{"line":17,"column":11,"offset":454},"indent":[]}},{"type":"text","value":" and ","position":{"start":{"line":17,"column":11,"offset":454},"end":{"line":17,"column":16,"offset":459},"indent":[]}},{"type":"inlineCode","value":"role=\"heading\" aria-level=\"5\"","position":{"start":{"line":17,"column":16,"offset":459},"end":{"line":17,"column":47,"offset":490},"indent":[]}}],"position":{"start":{"line":17,"column":5,"offset":448},"end":{"line":17,"column":47,"offset":490},"indent":[]}}],"position":{"start":{"line":17,"column":1,"offset":444},"end":{"line":17,"column":47,"offset":490},"indent":[]}},{"type":"listItem","spread":false,"checked":null,"children":[{"type":"paragraph","children":[{"type":"inlineCode","value":"<h6>","position":{"start":{"line":18,"column":5,"offset":495},"end":{"line":18,"column":11,"offset":501},"indent":[]}},{"type":"text","value":" and ","position":{"start":{"line":18,"column":11,"offset":501},"end":{"line":18,"column":16,"offset":506},"indent":[]}},{"type":"inlineCode","value":"role=\"heading\" aria-level=\"6\"","position":{"start":{"line":18,"column":16,"offset":506},"end":{"line":18,"column":47,"offset":537},"indent":[]}}],"position":{"start":{"line":18,"column":5,"offset":495},"end":{"line":18,"column":47,"offset":537},"indent":[]}}],"position":{"start":{"line":18,"column":1,"offset":491},"end":{"line":18,"column":47,"offset":537},"indent":[]}}],"position":{"start":{"line":13,"column":1,"offset":256},"end":{"line":18,"column":47,"offset":537},"indent":[1,1,1,1,1]}},{"type":"heading","depth":2,"children":[{"type":"text","value":"Goal: heading levels are available for search engines","position":{"start":{"line":20,"column":4,"offset":542},"end":{"line":20,"column":57,"offset":595},"indent":[]}}],"position":{"start":{"line":20,"column":1,"offset":539},"end":{"line":20,"column":57,"offset":595},"indent":[]}},{"type":"heading","depth":3,"children":[{"type":"text","value":"Solution: do not hide ","position":{"start":{"line":22,"column":5,"offset":601},"end":{"line":22,"column":27,"offset":623},"indent":[]}},{"type":"inlineCode","value":"<h1>","position":{"start":{"line":22,"column":27,"offset":623},"end":{"line":22,"column":33,"offset":629},"indent":[]}},{"type":"text","value":" or ","position":{"start":{"line":22,"column":33,"offset":629},"end":{"line":22,"column":37,"offset":633},"indent":[]}},{"type":"inlineCode","value":"role=\"heading\" aria-level=\"1\"","position":{"start":{"line":22,"column":37,"offset":633},"end":{"line":22,"column":68,"offset":664},"indent":[]}},{"type":"text","value":" in shadow DOM","position":{"start":{"line":22,"column":68,"offset":664},"end":{"line":22,"column":82,"offset":678},"indent":[]}}],"position":{"start":{"line":22,"column":1,"offset":597},"end":{"line":22,"column":82,"offset":678},"indent":[]}},{"type":"jsx","value":"<!-- id: ae82e69f-4655-4ee6-97b8-97886ac7d7b6 -->","position":{"start":{"line":24,"column":1,"offset":680},"end":{"line":24,"column":50,"offset":729},"indent":[]}},{"type":"heading","depth":2,"children":[{"type":"text","value":"Goal: headings can be browsed using a screen reader","position":{"start":{"line":26,"column":4,"offset":734},"end":{"line":26,"column":55,"offset":785},"indent":[]}}],"position":{"start":{"line":26,"column":1,"offset":731},"end":{"line":26,"column":55,"offset":785},"indent":[]}},{"type":"heading","depth":3,"children":[{"type":"text","value":"Solutions: mark up headers using ","position":{"start":{"line":28,"column":5,"offset":791},"end":{"line":28,"column":38,"offset":824},"indent":[]}},{"type":"inlineCode","value":"<h1>","position":{"start":{"line":28,"column":38,"offset":824},"end":{"line":28,"column":44,"offset":830},"indent":[]}},{"type":"text","value":"-","position":{"start":{"line":28,"column":44,"offset":830},"end":{"line":28,"column":45,"offset":831},"indent":[]}},{"type":"inlineCode","value":"<h6>","position":{"start":{"line":28,"column":45,"offset":831},"end":{"line":28,"column":51,"offset":837},"indent":[]}},{"type":"text","value":".","position":{"start":{"line":28,"column":51,"offset":837},"end":{"line":28,"column":52,"offset":838},"indent":[]}}],"position":{"start":{"line":28,"column":1,"offset":787},"end":{"line":28,"column":52,"offset":838},"indent":[]}},{"type":"paragraph","children":[{"type":"text","value":"Avoid using ","position":{"start":{"line":30,"column":1,"offset":840},"end":{"line":30,"column":13,"offset":852},"indent":[]}},{"type":"inlineCode","value":"<strong>","position":{"start":{"line":30,"column":13,"offset":852},"end":{"line":30,"column":23,"offset":862},"indent":[]}},{"type":"text","value":", ","position":{"start":{"line":30,"column":23,"offset":862},"end":{"line":30,"column":25,"offset":864},"indent":[]}},{"type":"inlineCode","value":"<b>","position":{"start":{"line":30,"column":25,"offset":864},"end":{"line":30,"column":30,"offset":869},"indent":[]}},{"type":"text","value":" or other elements with only a visual presentation of the heading, replace these with semantic HTML. ","position":{"start":{"line":30,"column":30,"offset":869},"end":{"line":30,"column":131,"offset":970},"indent":[]}},{"type":"jsx","value":"<!-- id: 08c2d301-7b91-4a1a-b5ed-cc582ac2ab72 -->","position":{"start":{"line":30,"column":131,"offset":970},"end":{"line":30,"column":180,"offset":1019},"indent":[]}}],"position":{"start":{"line":30,"column":1,"offset":840},"end":{"line":30,"column":180,"offset":1019},"indent":[]}},{"type":"heading","depth":3,"children":[{"type":"text","value":"Alternative: ","position":{"start":{"line":32,"column":5,"offset":1025},"end":{"line":32,"column":18,"offset":1038},"indent":[]}},{"type":"inlineCode","value":"role=\"heading\"","position":{"start":{"line":32,"column":18,"offset":1038},"end":{"line":32,"column":34,"offset":1054},"indent":[]}},{"type":"text","value":" with ","position":{"start":{"line":32,"column":34,"offset":1054},"end":{"line":32,"column":40,"offset":1060},"indent":[]}},{"type":"inlineCode","value":"aria-level","position":{"start":{"line":32,"column":40,"offset":1060},"end":{"line":32,"column":52,"offset":1072},"indent":[]}},{"type":"text","value":" is an alternative that works too.","position":{"start":{"line":32,"column":52,"offset":1072},"end":{"line":32,"column":86,"offset":1106},"indent":[]}}],"position":{"start":{"line":32,"column":1,"offset":1021},"end":{"line":32,"column":86,"offset":1106},"indent":[]}},{"type":"paragraph","children":[{"type":"inlineCode","value":"<h1>","position":{"start":{"line":34,"column":1,"offset":1108},"end":{"line":34,"column":7,"offset":1114},"indent":[]}},{"type":"text","value":"-","position":{"start":{"line":34,"column":7,"offset":1114},"end":{"line":34,"column":8,"offset":1115},"indent":[]}},{"type":"inlineCode","value":"<h6>","position":{"start":{"line":34,"column":8,"offset":1115},"end":{"line":34,"column":14,"offset":1121},"indent":[]}},{"type":"text","value":" is the preferred method, although there is no clear benefit.","position":{"start":{"line":34,"column":14,"offset":1121},"end":{"line":34,"column":75,"offset":1182},"indent":[]}}],"position":{"start":{"line":34,"column":1,"offset":1108},"end":{"line":34,"column":75,"offset":1182},"indent":[]}},{"type":"paragraph","children":[{"type":"text","value":"Replace ","position":{"start":{"line":36,"column":1,"offset":1184},"end":{"line":36,"column":9,"offset":1192},"indent":[]}},{"type":"inlineCode","value":"role=\"heading\"","position":{"start":{"line":36,"column":9,"offset":1192},"end":{"line":36,"column":25,"offset":1208},"indent":[]}},{"type":"text","value":" with ","position":{"start":{"line":36,"column":25,"offset":1208},"end":{"line":36,"column":31,"offset":1214},"indent":[]}},{"type":"inlineCode","value":"<h1>","position":{"start":{"line":36,"column":31,"offset":1214},"end":{"line":36,"column":37,"offset":1220},"indent":[]}},{"type":"text","value":"-","position":{"start":{"line":36,"column":37,"offset":1220},"end":{"line":36,"column":38,"offset":1221},"indent":[]}},{"type":"inlineCode","value":"<h6>","position":{"start":{"line":36,"column":38,"offset":1221},"end":{"line":36,"column":44,"offset":1227},"indent":[]}},{"type":"text","value":" ","position":{"start":{"line":36,"column":44,"offset":1227},"end":{"line":36,"column":45,"offset":1228},"indent":[]}},{"type":"jsx","value":"<!-- id: 475dd71f-37e4-464f-bf0f-e6e963625199 -->","position":{"start":{"line":36,"column":45,"offset":1228},"end":{"line":36,"column":94,"offset":1277},"indent":[]}}],"position":{"start":{"line":36,"column":1,"offset":1184},"end":{"line":36,"column":94,"offset":1277},"indent":[]}},{"type":"export","value":"export const _frontmatter = {}","position":{"start":{"line":39,"column":1,"offset":1280},"end":{"line":39,"column":31,"offset":1310},"indent":[]}}],"position":{"start":{"line":1,"column":1,"offset":0},"end":{"line":39,"column":31,"offset":1310}}},"scopeImports":[],"scopeIdentifiers":[],"rawMDXOutput":"/* @jsx mdx */\nimport { mdx } from '@mdx-js/react';\n/* @jsxRuntime classic */\n/* @jsx mdx */\nimport DefaultLayout from \"/Users/bobby/Sites/github.com/nl-design-system/documentatie/node_modules/gatsby-theme-docz/src/base/Layout.js\"\nexport const _frontmatter = {};\n\nconst layoutProps = {\n  _frontmatter\n};\nconst MDXLayout = DefaultLayout\nexport default function MDXContent({\n  components,\n  ...props\n}) {\n  return <MDXLayout {...layoutProps} {...props} components={components} mdxType=\"MDXLayout\">\n\n\n    {\n      /* @license CC0-1.0 */\n    }\n    <h1 {...{\n      \"id\": \"headings\"\n    }}>{`Headings`}</h1>\n    <p>{`This applies to multiple heading components:`}</p>\n    <ul>\n      <li parentName=\"ul\"><inlineCode parentName=\"li\">{`<h1>`}</inlineCode>{` and `}<inlineCode parentName=\"li\">{`role=\"heading\" aria-level=\"1\"`}</inlineCode></li>\n      <li parentName=\"ul\"><inlineCode parentName=\"li\">{`<h2>`}</inlineCode>{` and `}<inlineCode parentName=\"li\">{`role=\"heading\" aria-level=\"2\"`}</inlineCode></li>\n      <li parentName=\"ul\"><inlineCode parentName=\"li\">{`<h3>`}</inlineCode>{` and `}<inlineCode parentName=\"li\">{`role=\"heading\" aria-level=\"3\"`}</inlineCode></li>\n      <li parentName=\"ul\"><inlineCode parentName=\"li\">{`<h4>`}</inlineCode>{` and `}<inlineCode parentName=\"li\">{`role=\"heading\" aria-level=\"4\"`}</inlineCode></li>\n      <li parentName=\"ul\"><inlineCode parentName=\"li\">{`<h5>`}</inlineCode>{` and `}<inlineCode parentName=\"li\">{`role=\"heading\" aria-level=\"5\"`}</inlineCode></li>\n      <li parentName=\"ul\"><inlineCode parentName=\"li\">{`<h6>`}</inlineCode>{` and `}<inlineCode parentName=\"li\">{`role=\"heading\" aria-level=\"6\"`}</inlineCode></li>\n    </ul>\n    <h2 {...{\n      \"id\": \"goal-heading-levels-are-available-for-search-engines\"\n    }}>{`Goal: heading levels are available for search engines`}</h2>\n    <h3 {...{\n      \"id\": \"solution-do-not-hide-h1-or-roleheading-aria-level1-in-shadow-dom\"\n    }}>{`Solution: do not hide `}<inlineCode parentName=\"h3\">{`<h1>`}</inlineCode>{` or `}<inlineCode parentName=\"h3\">{`role=\"heading\" aria-level=\"1\"`}</inlineCode>{` in shadow DOM`}</h3>\n    {\n      /* id: ae82e69f-4655-4ee6-97b8-97886ac7d7b6 */\n    }\n    <h2 {...{\n      \"id\": \"goal-headings-can-be-browsed-using-a-screen-reader\"\n    }}>{`Goal: headings can be browsed using a screen reader`}</h2>\n    <h3 {...{\n      \"id\": \"solutions-mark-up-headers-using-h1-h6\"\n    }}>{`Solutions: mark up headers using `}<inlineCode parentName=\"h3\">{`<h1>`}</inlineCode>{`-`}<inlineCode parentName=\"h3\">{`<h6>`}</inlineCode>{`.`}</h3>\n    <p>{`Avoid using `}<inlineCode parentName=\"p\">{`<strong>`}</inlineCode>{`, `}<inlineCode parentName=\"p\">{`<b>`}</inlineCode>{` or other elements with only a visual presentation of the heading, replace these with semantic HTML. `}{\n        /* id: 08c2d301-7b91-4a1a-b5ed-cc582ac2ab72 */\n      }</p>\n    <h3 {...{\n      \"id\": \"alternative-roleheading-with-aria-level-is-an-alternative-that-works-too\"\n    }}>{`Alternative: `}<inlineCode parentName=\"h3\">{`role=\"heading\"`}</inlineCode>{` with `}<inlineCode parentName=\"h3\">{`aria-level`}</inlineCode>{` is an alternative that works too.`}</h3>\n    <p><inlineCode parentName=\"p\">{`<h1>`}</inlineCode>{`-`}<inlineCode parentName=\"p\">{`<h6>`}</inlineCode>{` is the preferred method, although there is no clear benefit.`}</p>\n    <p>{`Replace `}<inlineCode parentName=\"p\">{`role=\"heading\"`}</inlineCode>{` with `}<inlineCode parentName=\"p\">{`<h1>`}</inlineCode>{`-`}<inlineCode parentName=\"p\">{`<h6>`}</inlineCode>{` `}{\n        /* id: 475dd71f-37e4-464f-bf0f-e6e963625199 */\n      }</p>\n\n    </MDXLayout>;\n}\n\n;\nMDXContent.isMDXComponent = true;"}}